maurice_sdk/__init__.py
maurice_sdk/arm.py
maurice_sdk/drive.py
maurice_sdk/dynamixel.py
maurice_sdk/robot.py
maurice_sdk/uart.py
maurice_sdk-0.1.1.dist-info/LICENSE
maurice_sdk-0.1.1.dist-info/METADATA
maurice_sdk-0.1.1.dist-info/WHEEL
maurice_sdk-0.1.1.dist-info/top_level.txt
maurice_sdk-0.1.1.dist-info/RECORD
