Metadata-Version: 2.2
Name: maurice_sdk
Version: 0.1.1
Summary: A Python SDK for controlling the Maurice robot arm and drive system
Home-page: https://github.com/innate-inc/maurice_sdk.git
Author: Innate Inc
Author-email: vignesh@innate.bot
Classifier: Programming Language :: Python :: 3
Classifier: License :: OSI Approved :: MIT License
Classifier: Operating System :: OS Independent
Requires-Python: >=3.6
License-File: LICENSE
Requires-Dist: dynamixel_sdk
Requires-Dist: numpy
Requires-Dist: pyserial
Dynamic: author
Dynamic: author-email
Dynamic: classifier
Dynamic: description
Dynamic: description-content-type
Dynamic: home-page
Dynamic: requires-dist
Dynamic: requires-python
Dynamic: summary
